{
    "board": {
        "grid": [
            [
                ".",
                ".",
                "p",
                "o",
                ".",
                ".",
                ".",
                "."
            ],
            [
                ".",
                ".",
                ".",
                "o",
                ".",
                "x",
                ".",
                "."
            ],
            [
                ".",
                ".",
                "p",
                "o",
                "x",
                "o",
                "p",
                "."
            ],
            [
                ".",
                ".",
                ".",
                "x",
                "o",
                "o",
                "o",
                "p"
            ],
            [
                "p",
                "o",
                "x",
                "o",
                "o",
                "p",
                "p",
                "."
            ],
            [
                ".",
                "o",
                "o",
                "o",
                "o",
                "p",
                ".",
                "."
            ],
            [
                "p",
                "o",
                "p",
                "p",
                "p",
                ".",
                ".",
                "."
            ],
            [
                ".",
                ".",
                ".",
                ".",
                ".",
                ".",
                ".",
                "."
            ]
        ]
    },
    "is_playing": true,
    "menu": {
        "turns": 16,
        "player": "x",
        "pawns": [
            4,
            15
        ],
        "commands": {
            "P": "*P*lace a pawn",
            "A": "*A*bandon",
            "H": "Toggle *h*ints",
            "U": "*U*ndo a placement"
        },
        "hints": true
    },
    "time": 1576619106
}